{
    "response": {
        "header": {
            "resultCode": "00",
            "resultMsg": "정상적으로 처리되었습니다.",
            "requestParameter": {
                "cntntsNo": "18656"
            }
        },
        "body": {
            "item": {
                "adviseInfo": null,
                "clCodeNm": "잎&꽃보기식물",
                "cntntsNo": "18656",
                "distbNm": "바위취",
                "dlthtsCodeNm": "응애,온실가루이",
                "dlthtsManageInfo": null,
                "eclgyCodeNm": "일반형",
                "etcEraInfo": null,
                "flclrCodeNm": "분홍색,흰색",
                "flpodmtBigInfo": null,
                "flpodmtMddlInfo": null,
                "flpodmtSmallInfo": null,
                "fmlCodeNm": "범위귀과",
                "fmlNm": "063034",
                "fmldeSeasonCodeNm": null,
                "fmldecolrCodeNm": null,
                "fncltyInfo": "바위취는 우리나라 중부 이남의 반음지,음지에 조경용으로 식재하는는 상록 다년생 초본이다. 잎은 녹색에 연한 무늬가 있고, 뒷면은 자줏빛이 도는 붉은색이며 길이는 3~5㎝이다. 잎 가장자리에 치아 모양의 얕은 결각이 있으며 길이는 3~5㎝이며 꽃은 백색으로 꽃자루의 높이는 20~40㎝로서 곧게 서며 길이는 10~20㎝이고 짧은 홍자색의 선모가 있으며 줄기 꼭대기에서 핀다. 열매는 7~8월경에 달리고 길이는 4~5㎜로 원형이고 종자는 난형(달걀 모양)이며 관상용, 지피식물 또는 분화용으로 쓰이며, 전초는 약용으로 쓰인다.",
                "frtlzrInfo": "비료를 보통 요구함",
                "growthAraInfo": "20",
                "growthHgInfo": "20",
                "grwhTpCode": "082002",
                "grwhTpCodeNm": "16~20℃",
                "grwhstleCodeNm": "풀모양,로제트형",
                "grwtveCode": "090001",
                "grwtveCodeNm": "빠름",
                "hdCode": "083002",
                "hdCodeNm": "40 ~ 70%",
                "hgBigInfo": null,
                "hgMddlInfo": null,
                "hgSmallInfo": null,
                "ignSeasonCodeNm": "여름",
                "imageEvlLinkCours": null,
                "indoorpsncpacompositionCodeNm": "지피식물",
                "lefStleInfo": null,
                "lefcolrCodeNm": "녹색, 연두색,은색, 회색,빨강, 분홍, 자주색",
                "lefmrkCodeNm": "줄무늬",
                "lighttdemanddoCodeNm": "중간 광도(800~1,500 Lux),높은 광도(1,500~10,000 Lux)",
                "managedemanddoCode": "058002",
                "managedemanddoCodeNm": "보통 (약간 잘 견딤)",
                "managelevelCode": null,
                "managelevelCodeNm": null,
                "orgplceInfo": "일본, 중국, 한국, 대만",
                "pcBigInfo": null,
                "pcMddlInfo": null,
                "pcSmallInfo": null,
                "plntbneNm": "Saxifraga stolonifera",
                "plntzrNm": "strawberry saxifrage, magic carpet, mother of thousands",
                "postngplaceCodeNm": "거실 창측 (실내깊이 150~300cm),발코니 내측 (실내깊이 50~150cm),발코니 창측 (실내깊이 0~50cm)",
                "prpgtEraInfo": null,
                "prpgtmthCodeNm": "분주",
                "smellCode": null,
                "smellCodeNm": null,
                "soilInfo": null,
                "speclmanageInfo": null,
                "toxctyInfo": null,
                "volmeBigInfo": null,
                "volmeMddlInfo": null,
                "volmeSmallInfo": null,
                "vrticlBigInfo": null,
                "vrticlMddlInfo": null,
                "vrticlSmallInfo": null,
                "watercycleAutumnCode": "053003",
                "watercycleAutumnCodeNm": "토양 표면이 말랐을때 충분히 관수함",
                "watercycleSprngCode": "053003",
                "watercycleSprngCodeNm": "토양 표면이 말랐을때 충분히 관수함",
                "watercycleSummerCode": "053003",
                "watercycleSummerCodeNm": "토양 표면이 말랐을때 충분히 관수함",
                "watercycleWinterCode": "053004",
                "watercycleWinterCodeNm": "화분 흙 대부분 말랐을때 충분히 관수함",
                "widthBigInfo": null,
                "widthMddlInfo": null,
                "widthSmallInfo": null,
                "winterLwetTpCode": "057001",
                "winterLwetTpCodeNm": "0℃ 이하"
            }
        }
    }
}